{
    "os": "macOS-12.6-arm64-arm-64bit",
    "python": "3.9.15",
    "heartbeatAt": "2022-12-09T12:32:35.025171",
    "startedAt": "2022-12-09T12:32:34.276644",
    "docker": null,
    "cpu_count": 8,
    "cuda": null,
    "args": null,
    "state": "running",
    "program": "Notebook 1-jvsc-ff38ecb4-9393-45db-98a5-ef721d8c88360933c355-ef6f-4c09-aaee-9a2755c17c7c.ipynb",
    "root": "/Users/christianjensen/Documents/ATNLP",
    "git": {
        "remote": "https://github.com/christianjensen2903/ATNLP.git",
        "commit": "4b6a98b89fa59af9ffc460c7114b74fcdefc97f6"
    },
    "email": "cmj290300@gmail.com",
    "host": "Christians-MacBook-Air.local",
    "username": "christianjensen",
    "executable": "/opt/homebrew/opt/python@3.9/bin/python3.9"
}
